pinax/__init__.py
pinax/waitinglist/__init__.py
pinax/waitinglist/admin.py
pinax/waitinglist/apps.py
pinax/waitinglist/forms.py
pinax/waitinglist/models.py
pinax/waitinglist/receivers.py
pinax/waitinglist/signals.py
pinax/waitinglist/stats.py
pinax/waitinglist/urls.py
pinax/waitinglist/views.py
pinax/waitinglist/management/__init__.py
pinax/waitinglist/management/commands/__init__.py
pinax/waitinglist/management/commands/export_waitinglist_entries.py
pinax/waitinglist/management/commands/mail_out_survey_links.py
pinax/waitinglist/migrations/0001_initial.py
pinax/waitinglist/migrations/0002_auto_20160929_1624.py
pinax/waitinglist/migrations/__init__.py
pinax/waitinglist/templatetags/__init__.py
pinax/waitinglist/templatetags/pinax_waitinglist_tags.py
pinax/waitinglist/tests/__init__.py
pinax/waitinglist/tests/test.py
pinax/waitinglist/tests/tests.py
pinax/waitinglist/tests/urls.py
pinax_waitinglist-3.0.1.dist-info/AUTHORS
pinax_waitinglist-3.0.1.dist-info/LICENSE
pinax_waitinglist-3.0.1.dist-info/METADATA
pinax_waitinglist-3.0.1.dist-info/WHEEL
pinax_waitinglist-3.0.1.dist-info/top_level.txt
pinax_waitinglist-3.0.1.dist-info/RECORD
